pytrivialsql/__init__.py
pytrivialsql/postgres.py
pytrivialsql/sql.py
pytrivialsql/sqlite.py
pytrivialsql-0.1.20.dist-info/licenses/LICENSE
pytrivialsql-0.1.20.dist-info/METADATA
pytrivialsql-0.1.20.dist-info/WHEEL
pytrivialsql-0.1.20.dist-info/top_level.txt
pytrivialsql-0.1.20.dist-info/RECORD
