Metadata-Version: 2.4
Name: pytrivialsql
Version: 0.1.20
Summary: A trivial set of QOL bindings for SQL in Python
Author-email: inaimathi <leo.zovic@gmail.com>
Project-URL: Homepage, https://github.com/inaimathi/pytrivialsql
Project-URL: Issues, https://github.com/inaimathi/pytrivialsql/issues
Classifier: Programming Language :: Python :: 3
Classifier: License :: OSI Approved :: MIT License
Classifier: Operating System :: OS Independent
Requires-Python: >=3.8
License-File: LICENSE
Requires-Dist: psycopg[binary,pool]
Dynamic: license-file
